docling_mcp/__init__.py
docling_mcp/docling_cache.py
docling_mcp/docling_settings.py
docling_mcp/logger.py
docling_mcp/shared.py
docling_mcp/tools/__init__.py
docling_mcp/tools/applications.py
docling_mcp/tools/conversion.py
docling_mcp/tools/generation.py
docling_mcp/tools/manipulation.py
mseep_docling_mcp-0.4.0.dist-info/licenses/LICENSE
tests/__init__.py
tests/test_document_manipulation.py
tests/test_generation_tools.py
tests/test_mcp_server.py
mseep_docling_mcp-0.4.0.dist-info/METADATA
mseep_docling_mcp-0.4.0.dist-info/WHEEL
mseep_docling_mcp-0.4.0.dist-info/top_level.txt
mseep_docling_mcp-0.4.0.dist-info/RECORD
