Metadata-Version: 2.4
Name: mseep-docling-mcp
Version: 0.4.0
Summary: Running Docling as an agent using tools
Home-page: https://github.com/mseep
Author: mseep
Author-email: support@skydeck.ai
Maintainer: mseep
Maintainer-email: support@skydeck.ai
Keywords: mseep,mcp,message control protocol,agents,agentic,AI,artificial intelligence,document understanding,RAG,Docling
Classifier: Programming Language :: Python :: 3
Classifier: License :: OSI Approved :: MIT License
Classifier: Operating System :: OS Independent
Requires-Python: >=3.6
License-File: LICENSE
Requires-Dist: docling~=2.25
Requires-Dist: httpx>=0.28.1
Requires-Dist: llama-index>=0.12.33
Requires-Dist: llama-index-core>=0.12.28
Requires-Dist: llama-index-embeddings-huggingface>=0.5.2
Requires-Dist: llama-index-embeddings-openai>=0.3.1
Requires-Dist: llama-index-llms-ollama>=0.5.4
Requires-Dist: llama-index-node-parser-docling>=0.3.1
Requires-Dist: llama-index-readers-docling>=0.3.2
Requires-Dist: llama-index-readers-file>=0.4.7
Requires-Dist: llama-index-vector-stores-milvus>=0.7.2
Requires-Dist: mcp[cli]>=1.9.4
Requires-Dist: pydantic~=2.10
Requires-Dist: pydantic-settings~=2.4
Requires-Dist: python-dotenv>=1.1.0
Dynamic: author
Dynamic: author-email
Dynamic: classifier
Dynamic: description
Dynamic: description-content-type
Dynamic: home-page
Dynamic: keywords
Dynamic: license-file
Dynamic: maintainer
Dynamic: maintainer-email
Dynamic: requires-dist
Dynamic: requires-python
Dynamic: summary
